gutentag_world/__init__.py
gutentag_world-0.1.3.dist-info/LICENSE
gutentag_world-0.1.3.dist-info/METADATA
gutentag_world-0.1.3.dist-info/WHEEL
gutentag_world-0.1.3.dist-info/top_level.txt
gutentag_world-0.1.3.dist-info/RECORD
