Metadata-Version: 2.1
Name: gutentag_world
Version: 0.1.3
Summary: A simple package that prints 'Gutentag, World!'
Author-email: Sam Gutentag <sam@gutentag.dev>
Project-URL: Homepage, https://github.com/samgutentag/gutentag_world_python
Project-URL: Issues, https://github.com/samgutentag/gutentag_world_python/issues
Classifier: Programming Language :: Python :: 3
Classifier: License :: OSI Approved :: MIT License
Classifier: Operating System :: OS Independent
Requires-Python: >=3.8
License-File: LICENSE
